findmydevice/__init__.py
findmydevice/client.py
findmydevice/crypto.py
findmydevice-0.10.0.dist-info/LICENSE
findmydevice-0.10.0.dist-info/METADATA
findmydevice-0.10.0.dist-info/WHEEL
findmydevice-0.10.0.dist-info/top_level.txt
findmydevice-0.10.0.dist-info/RECORD
