Metadata-Version: 2.2
Name: findmydevice
Version: 0.10.0
Summary: A Python package for interacting with the findmydevice API.
Author-email: Dennis Schwertel <s@digitalkultur.net>
License: MIT License
Requires-Python: >=3.7
License-File: LICENSE
Requires-Dist: argon2-cffi
Requires-Dist: attrs
Requires-Dist: requests
Requires-Dist: cryptography
Provides-Extra: dev
Requires-Dist: pytest; extra == "dev"
Requires-Dist: ruff; extra == "dev"
